vsslctrl/__init__.py
vsslctrl/api_alpha.py
vsslctrl/api_base.py
vsslctrl/api_bravo.py
vsslctrl/core.py
vsslctrl/data_structure.py
vsslctrl/decorators.py
vsslctrl/device.py
vsslctrl/discovery.py
vsslctrl/event_bus.py
vsslctrl/exceptions.py
vsslctrl/group.py
vsslctrl/io.py
vsslctrl/settings.py
vsslctrl/track.py
vsslctrl/transport.py
vsslctrl/utils.py
vsslctrl/zone.py
vsslctrl-0.2.0.dist-info/licenses/LICENSE
vsslctrl-0.2.0.dist-info/METADATA
vsslctrl-0.2.0.dist-info/WHEEL
vsslctrl-0.2.0.dist-info/top_level.txt
vsslctrl-0.2.0.dist-info/RECORD
