Metadata-Version: 2.4
Name: vsslctrl
Version: 0.2.0
Summary: Package for controlling VSSL's range of streaming amplifiers
Author-email: vsslctrl <vsslcontrolled@proton.me>
Classifier: Development Status :: 4 - Beta
Classifier: Programming Language :: Python :: 3
Classifier: License :: OSI Approved :: MIT License
Classifier: Operating System :: OS Independent
Classifier: Intended Audience :: Developers
Classifier: Topic :: Home Automation
Classifier: Topic :: Software Development :: Libraries
Requires-Python: >=3.7
License-File: LICENSE
Provides-Extra: dev
Requires-Dist: pytest==8.1.1; extra == "dev"
Requires-Dist: pytest_asyncio==0.23.6; extra == "dev"
Provides-Extra: optional
Requires-Dist: zeroconf==0.132.2; extra == "optional"
Dynamic: license-file
